data_preprocessing_lib/__init__.py
data_preprocessing_lib/categorical_encoder.py
data_preprocessing_lib/data_type_converter.py
data_preprocessing_lib/datetime_handler.py
data_preprocessing_lib/feature_engineer.py
data_preprocessing_lib/missing_value_handler.py
data_preprocessing_lib/outlier_handler.py
data_preprocessing_lib/scaler.py
data_preprocessing_lib/text_cleaner.py
data_preprocessing_lib_byarat/__init__.py
data_preprocessing_lib_byarat/categorical_encoder.py
data_preprocessing_lib_byarat/data_type_converter.py
data_preprocessing_lib_byarat/datetime_handler.py
data_preprocessing_lib_byarat/feature_engineer.py
data_preprocessing_lib_byarat/missing_value_handler.py
data_preprocessing_lib_byarat/outlier_handler.py
data_preprocessing_lib_byarat/scaler.py
data_preprocessing_lib_byarat/text_cleaner.py
data_preprocessing_lib-0.1.1.dist-info/METADATA
data_preprocessing_lib-0.1.1.dist-info/WHEEL
data_preprocessing_lib-0.1.1.dist-info/top_level.txt
data_preprocessing_lib-0.1.1.dist-info/RECORD
